triplea/__init__.py
triplea/__version__.py
triplea/cli/__init__.py
triplea/cli/aaa.py
triplea/cli/analysis.py
triplea/cli/arepo.py
triplea/cli/config.py
triplea/cli/export.py
triplea/cli/export_article.py
triplea/cli/export_graph.py
triplea/cli/export_pretrain_llm.py
triplea/cli/go.py
triplea/cli/import_bib.py
triplea/cli/import_file.py
triplea/cli/main.py
triplea/cli/ner.py
triplea/cli/next.py
triplea/cli/pipeline.py
triplea/cli/search.py
triplea/cli/visualize.py
triplea/client/__init__.py
triplea/client/affiliation_parser.py
triplea/client/arxiv/__init__.py
triplea/client/pubmed/__init__.py
triplea/client/scigenius.py
triplea/client/topic_extraction.py
triplea/client/triple_extraction.py
triplea/config/__init__.py
triplea/config/environment_variable/.env.sample
triplea/config/settings.py
triplea/db/__init__.py
triplea/db/dal.py
triplea/db/database.py
triplea/db/mongo_nav.py
triplea/db/mongodb.py
triplea/db/tinydb.py
triplea/schemas/__init__.py
triplea/schemas/article.py
triplea/schemas/node.py
triplea/service/__init__.py
triplea/service/click_logger.py
triplea/service/graph/__init__.py
triplea/service/graph/analysis/__init__.py
triplea/service/graph/analysis/diameter.py
triplea/service/graph/analysis/ganalysis.py
triplea/service/graph/analysis/info.py
triplea/service/graph/analysis/neighbor_number.py
triplea/service/graph/export/__init__.py
triplea/service/graph/export/export.py
triplea/service/graph/export/neo4j.py
triplea/service/graph/extract/__init__.py
triplea/service/graph/extract/author.py
triplea/service/graph/extract/cited.py
triplea/service/graph/extract/country_based_co_authorship.py
triplea/service/graph/extract/keyword.py
triplea/service/graph/extract/reference.py
triplea/service/graph/extract/topic.py
triplea/service/import/__init__.py
triplea/service/llm/__init__.py
triplea/service/llm/calculate.py
triplea/service/llm/config_template.py
triplea/service/llm/init.py
triplea/service/llm/llm_profile_template_sample.json
triplea-0.0.5.dist-info/LICENSE
triplea-0.0.5.dist-info/METADATA
triplea-0.0.5.dist-info/WHEEL
triplea-0.0.5.dist-info/entry_points.txt
triplea-0.0.5.dist-info/RECORD
