Metadata-Version: 2.1
Name: triplea
Version: 0.0.5
Summary: Article Analysis Assistant
Home-page: https://github.com/EhsanBitaraf/triple-a
License: Apache-2.0
Keywords: graph,semantic-scholar,citation-graph
Author: EhsanBitaraf
Author-email: bitaraf.e@iums.ac.ir
Requires-Python: >=3.10,<4.0
Classifier: Environment :: Console
Classifier: Intended Audience :: Science/Research
Classifier: License :: OSI Approved :: Apache Software License
Classifier: Natural Language :: English
Classifier: Operating System :: OS Independent
Classifier: Programming Language :: Python :: 3
Classifier: Programming Language :: Python :: 3.10
Classifier: Programming Language :: Python :: 3.11
Classifier: Programming Language :: Python :: 3.12
Classifier: Topic :: Scientific/Engineering :: Visualization
Classifier: Topic :: Software Development :: Libraries :: Python Modules
Classifier: Topic :: Utilities
Requires-Dist: click (>=8.1.7,<9.0.0)
Requires-Dist: ipykernel (>=6.29.2,<7.0.0)
Requires-Dist: ipywidgets (>=8.1.2,<9.0.0)
Requires-Dist: langchain (>=0.1.6,<0.2.0)
Requires-Dist: langchain-openai (>=0.0.5,<0.0.6)
Requires-Dist: networkx (>=3.2.1,<4.0.0)
Requires-Dist: netwulf (>=0.1.5,<0.2.0)
Requires-Dist: nxviz (>=0.7.4,<0.8.0)
Requires-Dist: pydantic (>=2.6.1,<3.0.0)
Requires-Dist: pydantic-settings (>=2.1.0,<3.0.0)
Requires-Dist: pymongo (>=4.6.1,<5.0.0)
Requires-Dist: pypdf2 (>=3.0.1,<4.0.0)
Requires-Dist: tinydb (>=4.8.0,<5.0.0)
Requires-Dist: tomli (>=2.0.1,<3.0.0)
Requires-Dist: xmltodict (>=0.13.0,<0.14.0)
Project-URL: Repository, https://github.com/EhsanBitaraf/triple-a
